Karray/__init__.py
Karray/array.py
Karray/log.py
Karray/pi.py
Karray/trigonometry.py
Kbrain/__init__.py
Kbrain/layer/__init__.py
Kbrain/layer/layer.py
Kbrain/neural/__init__.py
Kbrain/neural/neural.py
Npai/__init__.py
Npai/layer/LayerUp.py
Npai/layer/__init__.py
Npai/neural/__init__.py
Npai/neural/neural.py
Kbrain-0.1.dist-info/METADATA
Kbrain-0.1.dist-info/WHEEL
Kbrain-0.1.dist-info/top_level.txt
Kbrain-0.1.dist-info/RECORD
