Metadata-Version: 2.1
Name: Kbrain
Version: 0.1
Summary: Kbrain is deeplearning package
Home-page: https://github.com/Kbrain2/KBrain.git
Author: Siu
Author-email: siukkokko@gmail.com
Classifier: Programming Language :: Python :: 3
Classifier: License :: OSI Approved :: MIT License
Classifier: Operating System :: OS Independent
